kaironviz/__init__.py
kaironviz/kschart.py
kaironviz/kschart_/drillChart.js
kaironviz/kschart_/drill_Chart_template.html
kaironviz/kschart_/kschart.js
kaironviz/kschart_/kschart_template.html
kaironviz/kschart_/kschart_template2.html
kaironviz/kschart_/treeDiagram.js
kaironviz/kschart_/tree_diagram_template.html
kaironviz/kschart_/wordCloud.js
kaironviz/kschart_/word_cloud_template.html
kaironviz-0.0.6.dist-info/METADATA
kaironviz-0.0.6.dist-info/WHEEL
kaironviz-0.0.6.dist-info/top_level.txt
kaironviz-0.0.6.dist-info/RECORD
