Metadata-Version: 2.1
Name: kaironviz
Version: 0.0.6
Summary: Data visualization for notebooks and html export
Home-page: UNKNOWN
Author: Kairon Team, Nimblework
Author-email: spandan.mondal@nimblework.com
License: MIT
Platform: UNKNOWN
Classifier: Programming Language :: Python :: 3
Classifier: License :: OSI Approved :: MIT License
Classifier: Operating System :: OS Independent
Requires-Dist: ipython
Requires-Dist: jsmin
Requires-Dist: numpy
Requires-Dist: pandas
